dby/__init__.py
dby-0.0.2.dist-info/METADATA
dby-0.0.2.dist-info/WHEEL
dby-0.0.2.dist-info/top_level.txt
dby-0.0.2.dist-info/RECORD
